scangen/__init__.py
scangen/internals.py
scangen-0.4a0.dist-info/LICENSE
scangen-0.4a0.dist-info/METADATA
scangen-0.4a0.dist-info/WHEEL
scangen-0.4a0.dist-info/top_level.txt
scangen-0.4a0.dist-info/RECORD
