Metadata-Version: 2.1
Name: scangen
Version: 0.4a0
Summary: Template-based scanner generator
Home-page: https://github.com/lggruspe/scangen
Author: Levi Gruspe
Author-email: mail.levig@gmail.com
License: UNKNOWN
Platform: UNKNOWN
Classifier: Programming Language :: Python :: 3
Classifier: License :: OSI Approved :: MIT License
Classifier: Operating System :: POSIX :: Linux
Requires-Dist: jinja2
